<annotation verified="no">
  <folder>1</folder>
  <filename>4793</filename>
  <path>G:\11\1\4793.png</path>
  <source>
    <database>Unknown</database>
  </source>
  <size>
    <width>640</width>
    <height>640</height>
    <depth>3</depth>
  </size>
  <segmented>0</segmented>
  <object>
    <type>robndbox</type>
    <name>defective4</name>
    <pose>Unspecified</pose>
    <truncated>0</truncated>
    <difficult>0</difficult>
    <robndbox>
      <cx>302.8911</cx>
      <cy>108.3204</cy>
      <w>154.8236</w>
      <h>90.7022</h>
      <angle>2.651593</angle>
    </robndbox>
  </object>
  <object>
    <type>robndbox</type>
    <name>defective2</name>
    <pose>Unspecified</pose>
    <truncated>0</truncated>
    <difficult>0</difficult>
    <robndbox>
      <cx>215.2862</cx>
      <cy>289.3418</cy>
      <w>217.8071</w>
      <h>163.9993</h>
      <angle>3.011593</angle>
    </robndbox>
  </object>
  <object>
    <type>robndbox</type>
    <name>defective3</name>
    <pose>Unspecified</pose>
    <truncated>0</truncated>
    <difficult>0</difficult>
    <robndbox>
      <cx>378.768</cx>
      <cy>257.3711</cy>
      <w>172.2532</w>
      <h>162.8065</h>
      <angle>0.77</angle>
    </robndbox>
  </object>
  <object>
    <type>robndbox</type>
    <name>defective1</name>
    <pose>Unspecified</pose>
    <truncated>0</truncated>
    <difficult>0</difficult>
    <robndbox>
      <cx>361.5131</cx>
      <cy>492.1953</cy>
      <w>157.4254</w>
      <h>178.3182</h>
      <angle>0.1</angle>
    </robndbox>
  </object>
  <object>
    <type>robndbox</type>
    <name>qualified</name>
    <pose>Unspecified</pose>
    <truncated>0</truncated>
    <difficult>0</difficult>
    <robndbox>
      <cx>485.8446</cx>
      <cy>358.3163</cy>
      <w>151.2846</w>
      <h>189.7979</h>
      <angle>0.31</angle>
    </robndbox>
  </object>
</annotation>
