<annotation verified="no">
  <folder>1</folder>
  <filename>4888</filename>
  <path>G:\11\1\4888.png</path>
  <source>
    <database>Unknown</database>
  </source>
  <size>
    <width>640</width>
    <height>640</height>
    <depth>3</depth>
  </size>
  <segmented>0</segmented>
  <object>
    <type>robndbox</type>
    <name>defective4</name>
    <pose>Unspecified</pose>
    <truncated>0</truncated>
    <difficult>0</difficult>
    <robndbox>
      <cx>215.7951</cx>
      <cy>215.6005</cy>
      <w>75.0131</w>
      <h>156.6045</h>
      <angle>3.041593</angle>
    </robndbox>
  </object>
  <object>
    <type>robndbox</type>
    <name>defective1</name>
    <pose>Unspecified</pose>
    <truncated>0</truncated>
    <difficult>0</difficult>
    <robndbox>
      <cx>233.7489</cx>
      <cy>411.2064</cy>
      <w>154.4026</w>
      <h>161.8197</h>
      <angle>2.811593</angle>
    </robndbox>
  </object>
  <object>
    <type>robndbox</type>
    <name>defective2</name>
    <pose>Unspecified</pose>
    <truncated>0</truncated>
    <difficult>0</difficult>
    <robndbox>
      <cx>390.003</cx>
      <cy>301.064</cy>
      <w>237.2483</w>
      <h>137.0354</h>
      <angle>1.911593</angle>
    </robndbox>
  </object>
  <object>
    <type>robndbox</type>
    <name>qualified</name>
    <pose>Unspecified</pose>
    <truncated>0</truncated>
    <difficult>0</difficult>
    <robndbox>
      <cx>400.5701</cx>
      <cy>105.4447</cy>
      <w>148.1207</w>
      <h>153.1385</h>
      <angle>3.011593</angle>
    </robndbox>
  </object>
  <object>
    <type>robndbox</type>
    <name>defective3</name>
    <pose>Unspecified</pose>
    <truncated>0</truncated>
    <difficult>0</difficult>
    <robndbox>
      <cx>448.1936</cx>
      <cy>534.5519</cy>
      <w>155.256</w>
      <h>159.7787</h>
      <angle>0.44</angle>
    </robndbox>
  </object>
</annotation>
