<annotation verified="no">
  <folder>1</folder>
  <filename>5034</filename>
  <path>G:\11\1\5034.png</path>
  <source>
    <database>Unknown</database>
  </source>
  <size>
    <width>3665</width>
    <height>1800</height>
    <depth>3</depth>
  </size>
  <segmented>0</segmented>
  <object>
    <type>robndbox</type>
    <name>defective2</name>
    <pose>Unspecified</pose>
    <truncated>0</truncated>
    <difficult>0</difficult>
    <robndbox>
      <cx>1759.1583</cx>
      <cy>803.2404</cy>
      <w>930.0413</w>
      <h>581.8976</h>
      <angle>0.65</angle>
    </robndbox>
  </object>
  <object>
    <type>robndbox</type>
    <name>qualified</name>
    <pose>Unspecified</pose>
    <truncated>0</truncated>
    <difficult>0</difficult>
    <robndbox>
      <cx>1755.7506</cx>
      <cy>1507.0712</cy>
      <w>650.4661</w>
      <h>407.1395</h>
      <angle>0.3</angle>
    </robndbox>
  </object>
</annotation>
